flask_model_management/__init__.py
flask_model_management/crud.py
flask_model_management/domain.py
flask_model_management/form.py
flask_model_management/manager.py
flask_model_management/static/css/bootstrap.min.css
flask_model_management/static/css/datatables.min.css
flask_model_management/static/css/flatpickr.min.css
flask_model_management/static/css/style.css
flask_model_management/static/img/favicon.ico
flask_model_management/static/js/app.js
flask_model_management/static/js/bootstrap.min.js
flask_model_management/static/js/datatables.min.js
flask_model_management/static/js/feather.min.js
flask_model_management/static/js/flatpickr.min.js
flask_model_management/static/js/jquery-3.5.1.min.js
flask_model_management/templates/base.html.jinja2
flask_model_management/templates/base_table.html.jinja2
flask_model_management/templates/index.html.jinja2
flask_model_management/templates/table.html.jinja2
flask_model_management/templates/components/fields.html.jinja2
flask_model_management/templates/components/flash.html.jinja2
flask_model_management/templates/components/macros.html.jinja2
flask_model_management/templates/operations/create.html.jinja2
flask_model_management/templates/operations/delete.html.jinja2
flask_model_management/templates/operations/read.html.jinja2
flask_model_management/templates/operations/update.html.jinja2
Flask_Model_Management-0.1.0.dist-info/LICENSE
Flask_Model_Management-0.1.0.dist-info/METADATA
Flask_Model_Management-0.1.0.dist-info/WHEEL
Flask_Model_Management-0.1.0.dist-info/top_level.txt
Flask_Model_Management-0.1.0.dist-info/RECORD
