Metadata-Version: 2.1
Name: Flask-Model-Management
Version: 0.1.0
Summary: Extension to manage SQLAlchemy models in Flask
Home-page: https://github.com/jackwardell/Flask-Model-Management
Author: jackwardell
Author-email: jack@wardell.xyz
License: UNKNOWN
Keywords: python
Platform: UNKNOWN
Classifier: Programming Language :: Python
Classifier: Programming Language :: Python :: 3
Classifier: Programming Language :: Python :: 3.6
Classifier: Programming Language :: Python :: 3.7
Classifier: Programming Language :: Python :: 3.8
Classifier: License :: OSI Approved :: MIT License
Classifier: Operating System :: OS Independent
Classifier: Natural Language :: English
Classifier: Intended Audience :: Developers
Classifier: Development Status :: 3 - Alpha
Requires-Python: >=3.6
Requires-Dist: Flask
Requires-Dist: Flask-SQLAlchemy
Requires-Dist: WTForms
Requires-Dist: Flask-WTF
Requires-Dist: attrs
